grexd/__init__.py
grexd/py.typed
grexd-0.1.1.data/data/share/doc/python-grexd/AUTHORS
grexd-0.1.1.data/data/share/doc/python-grexd/LICENSE
grexd-0.1.1.data/data/share/doc/python-grexd/README.md
grexd-0.1.1.data/scripts/grexd
grexd-0.1.1.dist-info/LICENSE
grexd-0.1.1.dist-info/METADATA
grexd-0.1.1.dist-info/WHEEL
grexd-0.1.1.dist-info/top_level.txt
grexd-0.1.1.dist-info/RECORD
